wxdat/__init__.py
wxdat/__main__.py
wxdat/config.py
wxdat/database.py
wxdat/metrics.py
wxdat/recorder.py
wxdat/version.py
wxdat/providers/__init__.py
wxdat/providers/accuweather.py
wxdat/providers/ambientwx.py
wxdat/providers/noaa.py
wxdat/providers/openweather.py
wxdat/providers/wunderground.py
wxdat-1.5.3.dist-info/METADATA
wxdat-1.5.3.dist-info/WHEEL
wxdat-1.5.3.dist-info/entry_points.txt
wxdat-1.5.3.dist-info/licenses/LICENSE
wxdat-1.5.3.dist-info/RECORD
