Metadata-Version: 2.4
Name: wxdat
Version: 1.5.3
Summary: Weather data explorer.
Author-email: jheddings <jheddings@gmail.com>
License-Expression: MIT
License-File: LICENSE
Requires-Python: <4,>=3.10
Requires-Dist: click<9,>=8.2.1
Requires-Dist: prometheus-client<0.23,>=0.22.1
Requires-Dist: psycopg2<3,>=2.9.10
Requires-Dist: pydantic<3,>=2.11.7
Requires-Dist: pyyaml<7,>=6.0.2
Requires-Dist: ratelimit<3,>=2.2.1
Requires-Dist: requests<3,>=2.32.5
Requires-Dist: sqlalchemy<3,>=2.0.43
Requires-Dist: wamu<0.4,>=0.3.1
